{"info":{"name":"reserva","schema":"https://schema.getpostman.com/json/collection/v2.1.0/collection.json"},"item":[{"name":"http://localhost:5000/reservas","request":{"method":"GET","url":{"raw":"http://localhost:5000/reservas?totalnoches=2","query":[{"key":"habitacionId","value":"101","disabled":true},{"key":"userId","value":"1","disabled":true},{"key":"totalnoches","value":"2"}],"variable":[],"protocol":"http","host":["localhost:5000"],"path":["reservas"],"port":"5000"}}},{"name":"http://localhost:5000/reservas","request":{"method":"POST","url":{"raw":"http://localhost:5000/reservas","protocol":"http","host":["localhost:5000"],"path":["reservas"],"port":"5000"}}},{"name":"http://localhost:5000/reservas","request":{"method":"DELETE","url":{"raw":"http://localhost:5000/reservas","protocol":"http","host":["localhost:5000"],"path":["reservas"],"port":"5000"}}},{"name":"http://localhost:5000/reservas","request":{"method":"PATCH","url":{"raw":"http://localhost:5000/reservas","protocol":"http","host":["localhost:5000"],"path":["reservas"],"port":"5000"}}}]}
